xbot2_gui_server/__init__.py
xbot2_gui_server/cartesian.py
xbot2_gui_server/concert.py
xbot2_gui_server/cosecosecose.py
xbot2_gui_server/dashboard.py
xbot2_gui_server/ecat.py
xbot2_gui_server/horizon.py
xbot2_gui_server/joint_device.py
xbot2_gui_server/joint_states.py
xbot2_gui_server/launcher.py
xbot2_gui_server/main.py
xbot2_gui_server/mkcert.py
xbot2_gui_server/parameters.py
xbot2_gui_server/plugin.py
xbot2_gui_server/process.py
xbot2_gui_server/screen_session.py
xbot2_gui_server/server.py
xbot2_gui_server/speech.py
xbot2_gui_server/stupid_speech_handler.py
xbot2_gui_server/theora_video.py
xbot2_gui_server/utils.py
xbot2_gui_server/visual.py
xbot2_gui_server/webui.py
xbot2_gui_server/xbot2_gui.py
xbot2_gui_server/proto/__init__.py
xbot2_gui_server/proto/generic_pb2.py
xbot2_gui_server/proto/jointstate_pb2.py
xbot2_gui_server/proto/process_output_pb2.py
xbot2_gui_server/proto/text_pb2.py
xbot2_gui_server/proto/theora_packet_pb2.py
xbot2_gui_server-2.7.3.dist-info/METADATA
xbot2_gui_server-2.7.3.dist-info/WHEEL
xbot2_gui_server-2.7.3.dist-info/entry_points.txt
xbot2_gui_server-2.7.3.dist-info/top_level.txt
xbot2_gui_server-2.7.3.dist-info/RECORD
