Metadata-Version: 2.1
Name: xbot2_gui_server
Version: 2.7.3
Summary: Backend for XBot2 QML GUI
Home-page: https://none
Author: Arturo Laurenzi
Author-email: arturo.laurenzi@iit.it
Project-URL: Bug Tracker, https://none
Classifier: Programming Language :: Python :: 3
Classifier: License :: OSI Approved :: MIT License
Classifier: Operating System :: OS Independent
Requires-Python: >=3.8
Requires-Dist: aiohttp
Requires-Dist: asyncudp
Requires-Dist: protobuf<5.29.9,>=5.29.0
